past_date2word/__init__.py
past_date2word/past_date2word.py
past_date2word-0.1.0.dist-info/LICENSE
past_date2word-0.1.0.dist-info/METADATA
past_date2word-0.1.0.dist-info/WHEEL
past_date2word-0.1.0.dist-info/top_level.txt
past_date2word-0.1.0.dist-info/RECORD
