Metadata-Version: 2.1
Name: past-date2word
Version: 0.1.0
Summary: past_date2word is library helps you to convert the past date to text
Home-page: https://github.com/TheAwiteb/past_date2word
Author: Awiteb
Author-email: Awiteb@hotmail.com
License: UNKNOWN
Keywords: date to text,date to word,to word,to text
Platform: UNKNOWN
Classifier: Programming Language :: Python :: 3.8
Classifier: Programming Language :: Python :: 3.9
Classifier: Programming Language :: Python :: 3.10
Classifier: License :: OSI Approved :: GNU General Public License v3 (GPLv3)
Classifier: Operating System :: OS Independent
Requires-Python: >=3.8
